streamlit_listen/__init__.py
streamlit_listen/frontend/build/asset-manifest.json
streamlit_listen/frontend/build/bootstrap.min.css
streamlit_listen/frontend/build/index.html
streamlit_listen/frontend/build/static/js/main.479106b8.js
streamlit_listen/frontend/build/static/js/main.479106b8.js.LICENSE.txt
streamlit_listen/frontend/build/static/js/main.479106b8.js.map
streamlit_listen-0.1.0.dist-info/LICENSE
streamlit_listen-0.1.0.dist-info/METADATA
streamlit_listen-0.1.0.dist-info/WHEEL
streamlit_listen-0.1.0.dist-info/top_level.txt
streamlit_listen-0.1.0.dist-info/RECORD
