Metadata-Version: 2.1
Name: streamlit-listen
Version: 0.1.0
Summary: Audio listener component for streamlit
Home-page: https://github.com/theevann/streamlit-audiorecorder
Author: Rafal Cegiela
Author-email: rcegiela@gmail.com
Requires-Python: >=3.6
License-File: LICENSE
Requires-Dist: streamlit >=0.63
